telepath/__init__.py
telepath/_callbacks.py
telepath/_decrs.py
telepath/_dto.py
telepath/_utils.py
telepath/logs.py
telepath/stateful_widgets.py
telepath/tgchat.py
telepath/tgmixins.py
pytelepath-1.2.1.dist-info/METADATA
pytelepath-1.2.1.dist-info/WHEEL
pytelepath-1.2.1.dist-info/RECORD
